clean_loop_timer/__init__.py
clean_loop_timer/timers.py
clean_loop_timer-0.2.0.dist-info/LICENSE
clean_loop_timer-0.2.0.dist-info/METADATA
clean_loop_timer-0.2.0.dist-info/WHEEL
clean_loop_timer-0.2.0.dist-info/top_level.txt
clean_loop_timer-0.2.0.dist-info/RECORD
