Metadata-Version: 2.1
Name: clean-loop-timer
Version: 0.2.0
Summary: Easy-to-use timer for profiling complex loops in dataset generation and neural network training
Home-page: https://github.com/tylerlum/clean_loop_timer
Author: Tyler Lum
Author-email: tylergwlum@gmail.com
License: UNKNOWN
Keywords: python,profiling,timer,loop
Platform: UNKNOWN
Classifier: Intended Audience :: Developers
Classifier: Topic :: Software Development :: Debuggers
Classifier: License :: OSI Approved :: MIT License
Classifier: Programming Language :: Python :: 3
License-File: LICENSE
Requires-Dist: pandas
Requires-Dist: tabulate
